odoo/addons/stock_picking_origin_reference_sale/README.rst
odoo/addons/stock_picking_origin_reference_sale/__init__.py
odoo/addons/stock_picking_origin_reference_sale/__manifest__.py
odoo/addons/stock_picking_origin_reference_sale/i18n/it.po
odoo/addons/stock_picking_origin_reference_sale/i18n/stock_picking_origin_reference_sale.pot
odoo/addons/stock_picking_origin_reference_sale/models/__init__.py
odoo/addons/stock_picking_origin_reference_sale/models/stock_picking.py
odoo/addons/stock_picking_origin_reference_sale/readme/CONTRIBUTORS.md
odoo/addons/stock_picking_origin_reference_sale/readme/DESCRIPTION.md
odoo/addons/stock_picking_origin_reference_sale/static/description/icon.png
odoo/addons/stock_picking_origin_reference_sale/static/description/index.html
odoo/addons/stock_picking_origin_reference_sale/tests/__init__.py
odoo/addons/stock_picking_origin_reference_sale/tests/test_stock_picking_origin_reference_sale.py
odoo_addon_stock_picking_origin_reference_sale-18.0.1.0.0.2.dist-info/METADATA
odoo_addon_stock_picking_origin_reference_sale-18.0.1.0.0.2.dist-info/WHEEL
odoo_addon_stock_picking_origin_reference_sale-18.0.1.0.0.2.dist-info/top_level.txt
odoo_addon_stock_picking_origin_reference_sale-18.0.1.0.0.2.dist-info/RECORD
