Metadata-Version: 2.1
Name: odoo-addon-stock_picking_origin_reference_sale
Version: 18.0.1.0.0.2
Requires-Python: >=3.10
Requires-Dist: odoo-addon-stock_picking_origin_reference==18.0.*
Requires-Dist: odoo==18.0.*
Summary: Transfer to Sales Order navigation from the Source Document.
Home-page: https://github.com/OCA/stock-logistics-workflow
License: AGPL-3
Author: ForgeFlow, Odoo Community Association (OCA)
Author-email: support@odoo-community.org
Classifier: Programming Language :: Python
Classifier: Framework :: Odoo
Classifier: Framework :: Odoo :: 18.0
Classifier: License :: OSI Approved :: GNU Affero General Public License v3
